phonemizer/__init__.py
phonemizer/backend/__init__.py
phonemizer/backend/base.py
phonemizer/backend/espeak/__init__.py
phonemizer/backend/espeak/api.py
phonemizer/backend/espeak/base.py
phonemizer/backend/espeak/espeak.py
phonemizer/backend/espeak/language_switch.py
phonemizer/backend/espeak/mbrola.py
phonemizer/backend/espeak/voice.py
phonemizer/backend/espeak/words_mismatch.py
phonemizer/backend/espeak/wrapper.py
phonemizer/backend/festival/__init__.py
phonemizer/backend/festival/festival.py
phonemizer/backend/festival/lispy.py
phonemizer/backend/segments.py
phonemizer/logger.py
phonemizer/phonemize.py
phonemizer/punctuation.py
phonemizer/separator.py
phonemizer/share/festival/phonemize.scm
phonemizer/share/segments/chintang.g2p
phonemizer/share/segments/cree.g2p
phonemizer/share/segments/inuktitut.g2p
phonemizer/share/segments/japanese.g2p
phonemizer/share/segments/sesotho.g2p
phonemizer/share/segments/yucatec.g2p
phonemizer/utils.py
pozalabs_phonemizer-3.3.0.dist-info/LICENSE
pozalabs_phonemizer-3.3.0.dist-info/METADATA
pozalabs_phonemizer-3.3.0.dist-info/WHEEL
pozalabs_phonemizer-3.3.0.dist-info/RECORD
