Metadata-Version: 2.1
Name: pozalabs-phonemizer
Version: 3.3.0
Summary: Simple text to phones converter for multiple languages
License: GPL3
Keywords: linguistics,G2P,phone,festival,espeak,TTS
Author: pozalabs
Author-email: contact@pozalabs.com
Requires-Python: >=3.11,<4.0
Classifier: License :: OSI Approved :: GNU General Public License v3 or later (GPLv3+)
Classifier: License :: Other/Proprietary License
Classifier: Operating System :: OS Independent
Classifier: Programming Language :: Python :: 3
Classifier: Programming Language :: Python :: 3.11
Classifier: Programming Language :: Python :: 3.12
Requires-Dist: attrs (>=18.1)
Requires-Dist: dlinfo (>=1.2.1,<2.0.0)
Requires-Dist: joblib (>=1.4.2,<2.0.0)
Requires-Dist: segments (>=2.2.1,<3.0.0)
Requires-Dist: typing-extensions (>=4.12.2,<5.0.0)
